pycps/__init__.py
pycps/api.py
pycps/compat.py
pycps/cpsm2014-01.ddf
pycps/data_dictionary_fixups.py
pycps/downloaders.py
pycps/logging.json
pycps/make_data_store.py
pycps/merge.py
pycps/monthly_data_fixups.py
pycps/parsers.py
pycps/settings.json
pycps/setup_logging.py
pycps/tests/__init__.py
pycps/tests/test_dd_fixups.py
pycps/tests/test_downloaders.py
pycps/tests/test_merge.py
pycps/tests/test_parsers.py
python_cps-0.4.0.dist-info/DESCRIPTION.rst
python_cps-0.4.0.dist-info/entry_points.txt
python_cps-0.4.0.dist-info/METADATA
python_cps-0.4.0.dist-info/metadata.json
python_cps-0.4.0.dist-info/RECORD
python_cps-0.4.0.dist-info/top_level.txt
python_cps-0.4.0.dist-info/WHEEL
