Metadata-Version: 2.0
Name: python-cps
Version: 0.4.0
Summary: A python package for working with the[Current Population Survey](http://www.census.gov/cps/).
Home-page: http://github.com/TomAugspurger/pycps
Author: Tom Augspurger
Author-email: tom.w.augspurger@gmail.com
License: MIT
Keywords: pycps,cps
Platform: UNKNOWN
Classifier: Development Status :: 3 - Alpha
Classifier: Intended Audience :: Developers
Classifier: License :: OSI Approved :: MIT License
Classifier: Programming Language :: Python :: 3
Classifier: Programming Language :: Python :: 3.1
Classifier: Programming Language :: Python :: 3.2
Classifier: Programming Language :: Python :: 3.3
Classifier: Programming Language :: Python :: 2
Classifier: Programming Language :: Python :: 2.7
Requires-Dist: arrow (>=0.4.0)
Requires-Dist: requests (>=2.4.0)
Requires-Dist: pathlib (>=1.0.1)
Requires-Dist: lxml (>=3.3.5)
Requires-Dist: numpy (>=1.8.0)
Requires-Dist: pandas (>=0.14.1)
